{
"id": "6D34__02",
"file": "6D34.html",
"segments": [
{
"i": 703,
"t": "Sübut:"
},
{
"i": 704,
"t": "təkrarlanan paterni klinik diaqnoz tələb edir."
},
{
"i": 705,
"t": "Mif 3: \"Yalnız hüquqi cəza\""
},
{
"i": 706,
"t": "Sübut:"
},
{
"i": 707,
"t": "klinik müdaxilə residiv azaldır."
},
{
"i": 708,
"t": "11. Mənbələr"
},
{
"i": 709,
"t": "WHO. ICD-11. 6D34 Frotteuristic disorder. 2024."
},
{
"i": 710,
"t": "APA. DSM-5-TR. 2022."
},
{
"i": 711,
"t": "Thibaut F. et al. WFSBP. World J Biol Psychiatry 2020."
},
{
"i": 712,
"t": "← 6D33"
},
{
"i": 713,
"t": "SADİSTİK CİNSİ POZUNTU"
},
{
"i": 714,
"t": "↑ Fəsil"
},
{
"i": 715,
"t": "Yuxarı"
},
{
"i": 716,
"t": "Bağla"
},
{
"i": 717,
"t": "КП"
},
{
"i": 718,
"t": "Kitabın sifarişi"
},
{
"i": 719,
"t": "Kitab çap nəşrinə hazırlanır. İlk oxucular arasında olmaq istəyirsinizsə, məlumatlarınızı buraxın — nəşr olunan kimi dərhal sizinlə əlaqə saxlayacağıq."
},
{
"i": 720,
"t": "Ad Soyad"
},
{
"i": 721,
"t": "Adınız və soyadınız"
},
{
"i": 722,
"t": "Mobil nömrə"
},
{
"i": 723,
"t": "+994 XX XXX XX XX"
},
{
"i": 724,
"t": "Sifariş et"
},
{
"i": 725,
"t": "Təşəkkür edirik!"
},
{
"i": 726,
"t": "Kitab nəşr olunan kimi sizinlə əlaqə saxlayacağıq."
}
]
}