{
"id": "6E62__02",
"file": "6E62.html",
"segments": [
{
"i": 697,
"t": "Sübut:"
},
{
"i": 698,
"t": "klinik narahatlıq tibbi vəziyyətin gedişini pisləşdirir; müdaxilə tələb edir."
},
{
"i": 699,
"t": "Mif 2: \"Hipertiroidizmdə antianksiolitik birinci sıra\""
},
{
"i": 700,
"t": "Sübut:"
},
{
"i": 701,
"t": "tireoid korreksiyası birinci; β-blokator (propranolol) simptomatik adjunkt."
},
{
"i": 702,
"t": "Mif 3: \"Kafein təhlükəsizdir\""
},
{
"i": 703,
"t": "Sübut:"
},
{
"i": 704,
"t": "yüksək doza panik, narahatlıq, taxikardiya yaradar; məhdudlaşdırma tövsiyə olunur."
},
{
"i": 705,
"t": "11. Mənbələr"
},
{
"i": 706,
"t": "WHO. ICD-11. 6E62 Secondary anxiety syndrome. 2024."
},
{
"i": 707,
"t": "APA. DSM-5-TR. 2022."
},
{
"i": 708,
"t": "Levenson J.L. APA Textbook of Psychosomatic Medicine 2018."
},
{
"i": 709,
"t": "← 6E61"
},
{
"i": 710,
"t": "İKİNCİLİ AFFEKTİV SİND"
},
{
"i": 711,
"t": "↑ Fəsil"
},
{
"i": 712,
"t": "Yuxarı"
},
{
"i": 713,
"t": "Bağla"
},
{
"i": 714,
"t": "КП"
},
{
"i": 715,
"t": "Kitabın sifarişi"
},
{
"i": 716,
"t": "Kitab çap nəşrinə hazırlanır. İlk oxucular arasında olmaq istəyirsinizsə, məlumatlarınızı buraxın — nəşr olunan kimi dərhal sizinlə əlaqə saxlayacağıq."
},
{
"i": 717,
"t": "Ad Soyad"
},
{
"i": 718,
"t": "Adınız və soyadınız"
},
{
"i": 719,
"t": "Mobil nömrə"
},
{
"i": 720,
"t": "+994 XX XXX XX XX"
},
{
"i": 721,
"t": "Sifariş et"
},
{
"i": 722,
"t": "Təşəkkür edirik!"
},
{
"i": 723,
"t": "Kitab nəşr olunan kimi sizinlə əlaqə saxlayacağıq."
}
]
}