[{"i": 1002, "t": "Laugeson E.A., Frankel F., Gantman A., Dillon A.R., Mogil C. Evidence-based social skills training for adolescents with autism spectrum disorders: the UCLA PEERS program. J Autism Dev Disord 2012;42(6):1025–1036."}, {"i": 1003, "t": "Lai M.C., Baron-Cohen S. Identifying the lost generation of adults with autism spectrum conditions. Lancet Psychiatry 2015;2(11):1013–1027."}, {"i": 1004, "t": "Berkowitz A.L., Miller M.B., Mir S.A. et al. Glioproliferative lesion of the spinal cord as a complication of \"stem-cell tourism\". NEJM 2016;375(2):196–198."}, {"i": 1005, "t": "← 6A01"}, {"i": 1006, "t": "НАРУШЕНИЕ РАЗВИТИЯ РЕЧИ И ЯЗЫКА"}, {"i": 1007, "t": "↑ Глава"}, {"i": 1008, "t": "СПЕЦИФИЧЕСКОЕ РАССТРОЙСТВО ОБУЧЕНИЯ"}, {"i": 1009, "t": "6A03 →"}, {"i": 1010, "t": "Вверх"}, {"i": 1011, "t": "Закрыть"}, {"i": 1012, "t": "КП"}, {"i": 1013, "t": "Заказ книги"}, {"i": 1014, "t": "Книга готовится к печатному изданию. Если вы хотите быть среди первых читателей, оставьте свои данные — мы свяжемся с вами сразу после публикации."}, {"i": 1015, "t": "Ad Soyad"}, {"i": 1016, "t": "Ваше имя и фамилия"}, {"i": 1017, "t": "Номер мобильного телефона"}, {"i": 1018, "t": "+994 XX XXX XX XX"}, {"i": 1019, "t": "Заказать"}, {"i": 1020, "t": "Благодарим вас!"}, {"i": 1021, "t": "Мы свяжемся с вами, как только книга будет опубликована."}]