[{"i": 710, "t": "Доказательства:"}, {"i": 711, "t": "«Апскёртинг», скрытая камера — сексуальное преступление; требуется клиническое и правовое вмешательство."}, {"i": 712, "t": "Миф 4: «Лечение неэффективно»"}, {"i": 713, "t": "Доказательства:"}, {"i": 714, "t": "КПТ и фармакотерапия эффективны."}, {"i": 715, "t": "11. Источники"}, {"i": 716, "t": "WHO. ICD-11. 6D31 Voyeuristic disorder. 2024."}, {"i": 717, "t": "APA. DSM-5-TR. 2022."}, {"i": 718, "t": "Thibaut F. et al. WFSBP. World J Biol Psychiatry 2020."}, {"i": 719, "t": "← 6D30"}, {"i": 720, "t": "ЭКСГИБИЦИОНИЗМ"}, {"i": 721, "t": "↑ Глава"}, {"i": 722, "t": "ПЕДОФИЛИЧЕСКОЕ РАССТРОЙСТВО"}, {"i": 723, "t": "6D32 →"}, {"i": 724, "t": "Вверх"}, {"i": 725, "t": "Закрыть"}, {"i": 726, "t": "КП"}, {"i": 727, "t": "Заказ книги"}, {"i": 728, "t": "Книга готовится к печатному изданию. Если вы хотите быть среди первых читателей, оставьте свои данные — мы свяжемся с вами сразу после публикации."}, {"i": 729, "t": "Ad Soyad"}, {"i": 730, "t": "Ваше имя и фамилия"}, {"i": 731, "t": "Номер мобильного телефона"}, {"i": 732, "t": "+994 XX XXX XX XX"}, {"i": 733, "t": "Заказать"}, {"i": 734, "t": "Благодарим вас!"}, {"i": 735, "t": "Мы свяжемся с вами, как только книга будет опубликована."}]