[{"i": 674, "t": "6. Diaqnoz"}, {"i": 675, "t": "6.1 Vahid diaqnostik meyarlar"}, {"i": 676, "t": "A."}, {"i": 677, "t": "Marked fear in one or more social situations — being observed or evaluated by others."}, {"i": 678, "t": "B."}, {"i": 679, "t": "The patient fears humiliation, rejection by others, or harming others."}, {"i": 680, "t": "C."}, {"i": 681, "t": "Situations almost always provoke fear."}, {"i": 682, "t": "D."}, {"i": 683, "t": "Avoidance or endurance with intense discomfort."}, {"i": 684, "t": "E."}, {"i": 685, "t": "Fear is disproportionate to the social situation."}, {"i": 686, "t": "F."}, {"i": 687, "t": "≥6 months duration (DSM-5-TR)."}, {"i": 688, "t": "G."}, {"i": 689, "t": "Funksional pozulma."}, {"i": 690, "t": "H."}, {"i": 691, "t": "Not fully explained by another mental disorder or medical condition."}, {"i": 692, "t": "6.2 Source-specific specifications"}, {"i": 693, "t": "DSM-5-TR — \"performance only\" specifier (limited to performance situations)."}, {"i": 694, "t": "ICD-11 — parallel; in children, peer setting is also assessed (not only with adults)."}, {"i": 695, "t": "NICE CG159 (Social anxiety disorder: recognition, assessment and treatment, 2013) — individual CBT first-line."}, {"i": 696, "t": "6.3 Diaqnostika alqoritmi"}, {"i": 697, "t": "Clinical interview."}, {"i": 698, "t": "SCID-5, MINI."}, {"i": 699, "t": "Liebowitz Social Anxiety Scale (LSAS), SPIN (Social Phobia Inventory) — scale and monitoring."}, {"i": 700, "t": "Comorbidity (MDD, other anxiety, alcohol use)."}, {"i": 701, "t": "6.4 Differensial diaqnostika"}, {"i": 702, "t": "State"}, {"i": 703, "t": "Differentiating"}, {"i": 704, "t": "Aqorafobiya (6B02)"}, {"i": 705, "t": "Difficult escape, help absent; social evaluation absent."}, {"i": 706, "t": "Spesifik fobiya (6B03)"}, {"i": 707, "t": "Konkret obyekt/situasiya."}, {"i": 708, "t": "Panik (6B01)"}, {"i": 709, "t": "Attack is unexpected."}, {"i": 710, "t": "Avoidant personality disorder"}, {"i": 711, "t": "Persistent pattern, broader; comorbidity is common."}, {"i": 712, "t": "Autizm spektri (6A02)"}, {"i": 713, "t": "Social-communication deficit early onset; social interest variable."}, {"i": 714, "t": "Selektiv mutizm (6B06)"}, {"i": 715, "t": "Loss of speech in a specific context."}, {"i": 716, "t": "Body dysmorphic disorder (6B21)"}, {"i": 717, "t": "Appearance-based anxiety."}, {"i": 718, "t": "7. Examination and assessment"}, {"i": 719, "t": "LSAS — gold standard scale (24 items)."}, {"i": 720, "t": "SPIN — short screening (17 items)."}, {"i": 721, "t": "BFNE (Brief Fear of Negative Evaluation)."}, {"i": 722, "t": "8. Treatment"}, {"i": 723, "t": "8.1 General principles (NICE CG159 · CANMAT 2014)"}, {"i": 724, "t": "Individual CBT (Clark D.M. model) first-line"}, {"i": 725, "t": "— redirecting self-focused attention, video feedback, behavioral experiments, cognitive restructuring, in vivo exposure. 12–16 sessions. NICE CG159 — individual CBT superior to group CBT."}, {"i": 726, "t": "SSRI and SNRI first-line pharmacotherapy"}, {"i": 727, "t": "– escitalopram, sertraline, paroxetine (FDA approved), venlafaxine (FDA approved)."}, {"i": 728, "t": "Second-order"}, {"i": 729, "t": "moclobemide (RIMA, approved in Europe), pregabalin (evidence limited), gabapentin."}, {"i": 730, "t": "benzodiazepine"}, {"i": 731, "t": "— only short-term for a specific situation (e.g., prior to performance); not sustained."}, {"i": 732, "t": "β-blocker (propranolol)."}, {"i": 733, "t": "— in performance subtype, 1–2 hours before performance; ineffective in social reciprocal interaction."}, {"i": 734, "t": "Duration of treatment"}, {"i": 735, "t": "— after remission ≥ 12 months."}, {"i": 736, "t": "Alcohol use"}, {"i": 737, "t": "— as a form of self-medication; requires special attention and parallel intervention."}, {"i": 738, "t": "8.2 Source-Specific Clarifications"}, {"i": 739, "t": "NICE CG159 (2013) — individual CBT (Clark) first-line; SSRIs alternative; group CBT or self-help may be suitable for some patients."}, {"i": 740, "t": "CANMAT 2014 — first-line escitalopram, sertraline, paroxetine, venlafaxine."}, {"i": 741, "t": "Mayo-Wilson E. et al. Lancet Psychiatry 2014 network meta-analysis — individual CBT has the greatest effect; SSRIs second."}, {"i": 742, "t": "Treatment methodologies"}, {"i": 743, "t": "Klark KDT Modeli (Clark)"}, {"i": 744, "t": "— Specifically developed for social anxiety; external redirection of self-focused attention, video feedback (seeing one's performance through others' eyes), behavioral experiments (testing fearful beliefs), in vivo exposure. Evidence: Clark D.M. et al. J Consult Clin Psychol 2003 RCT — experimental individual CBT superior to other interventions."}, {"i": 745, "t": "Haymberq Qrup KDT (Heimberg)"}, {"i": 746, "t": "— 12-session group format; Heimberg R.G. model. Effective, but relatively weaker than individual CBT (NICE CG159)."}, {"i": 747, "t": "Internet-based cognitive behavioral therapy (iCBT)"}, {"i": 748, "t": "Andersson G. et al. Comparison of self-help internet-based cognitive behavioral therapy (ICBT) with therapist-supported ICBT to individual cognitive behavioral therapy (CBT)."}, {"i": 749, "t": "Liebowitz Social Anxiety Scale (LSAS — Liebowitz Social Anxiety Scale)"}, {"i": 750, "t": "24 items (12 interactions + 12 performance); gold standard."}, {"i": 751, "t": "Social Phobia Inventory (SPIN)"}, {"i": 752, "t": "17 items; brief screening."}, {"i": 753, "t": "9. Proqnoz"}, {"i": 754, "t": "Chronic course, high relapse rate without treatment."}, {"i": 755, "t": "CBT and SSRIs result in significant improvement in most patients."}, {"i": 756, "t": "Early onset and avoidant personality comorbidity as a poor prognosis marker."}, {"i": 757, "t": "10. Myths and misconceptions"}, {"i": 758, "t": "Myth 1: \"Social anxiety — ordinary 'shyness about life', does not require treatment\""}, {"i": 759, "t": "Evidence:"}, {"i": 760, "t": "Social anxiety disorder is associated with functional impairment, academic and occupational limitations, risk of depression and alcohol use; it is evaluated as a medical condition."}, {"i": 761, "t": "Myth 2: \"The patient can live a normal life by completely avoiding social situations\""}, {"i": 762, "t": "Evidence:"}, {"i": 763, "t": "Avoidance symptoms strengthen and lead to isolation; exposure is the main therapeutic mechanism."}, {"i": 764, "t": "Myth 3: \"Alcohol 'treats' social anxiety\""}, {"i": 765, "t": "Evidence:"}, {"i": 766, "t": "Alcohol provides short-term relief but long-term exacerbates distress and leads to alcohol use disorder; prevalence of this combination is 20–40%."}, {"i": 767, "t": "Myth 4: \"Benzodiazepines are effective long-term for social anxiety\""}, {"i": 768, "t": "Evidence:"}, {"i": 769, "t": "Short-term effect; addiction potential; CBT or SSRIs superior."}, {"i": 770, "t": "Myth 5: \"Propranolol is effective for all forms of social anxiety\""}, {"i": 771, "t": "Evidence:"}, {"i": 772, "t": "propranolol only"}, {"i": 773, "t": "in the performance subtype"}, {"i": 774, "t": "(effective before exit); ineffective in social interaction (party, relationships)."}, {"i": 775, "t": "Myth 6: \"The patient has avoidant personality disorder, so treatment is unresponsive\""}, {"i": 776, "t": "Evidence:"}, {"i": 777, "t": "Comorbid avoidant personality patient may also respond to standard interventions; long-term CBT or schema therapy."}, {"i": 778, "t": "Myth 7: Only hypnotherapy or NLP cures quickly"}, {"i": 779, "t": "Evidence:"}, {"i": 780, "t": "No evidence base; CBT and SSRIs are gold standard."}, {"i": 781, "t": "Myth 8: Cannabis (CBD) is a safe alternative for social anxiety"}, {"i": 782, "t": "Evidence:"}, {"i": 783, "t": "initial studies exist, but insufficient for clinical recommendation; THC may worsen distress."}, {"i": 784, "t": "11. Sources"}, {"i": 785, "t": "WHO. ICD-11. 6B04 Social anxiety disorder. 2024."}, {"i": 786, "t": "APA. DSM-5-TR. 2022."}, {"i": 787, "t": "NICE CG159. Social anxiety disorder: recognition, assessment and treatment. 2013."}, {"i": 788, "t": "Katzman M.A. et al. CANMAT 2014. BMC Psychiatry 2014;14(Suppl 1):S1."}, {"i": 789, "t": "Mayo-Wilson E. et al. Psychological and pharmacological interventions for social anxiety disorder in adults: a systematic review and network meta-analysis. Lancet Psychiatry 2014;1(5):368–376."}, {"i": 790, "t": "Clark D.M., Ehlers A., McManus F. et al. Cognitive therapy versus fluoxetine in generalized social phobia: a randomized placebo-controlled trial. J Consult Clin Psychol 2003;71(6):1058–1067."}, {"i": 791, "t": "Liebowitz M.R. Social phobia. Mod Probl Pharmacopsychiatry 1987;22:141–173."}, {"i": 792, "t": "6B03"}, {"i": 793, "t": "SPECIFIC PHOBIA"}, {"i": 794, "t": "↑ Chapter"}, {"i": 795, "t": "SEPARATION ANXIETY DISORDER"}, {"i": 796, "t": "6B05 →"}, {"i": 797, "t": "Upper"}, {"i": 798, "t": "Close"}, {"i": 799, "t": "CP"}, {"i": 800, "t": "Ordering the book"}, {"i": 801, "t": "The book is being prepared for print publication. If you want to be among the first readers, leave your information — we will contact you immediately upon publication."}, {"i": 802, "t": "Ad Soyad"}, {"i": 803, "t": "Your first and last name"}, {"i": 804, "t": "Mobile number"}, {"i": 805, "t": "+994 XX XXX XX XX"}, {"i": 806, "t": "Order"}, {"i": 807, "t": "Thank you!"}, {"i": 808, "t": "We will contact you as soon as the book is published."}]